{
  "source": "0511Wextra.xlsx",
  "has_extra_items": true,
  "items": [
    {
      "sno": 1,
      "desc": "Rewiring of light point/ fan point/ exha",
      "qty": "",
      "rate": "",
      "amt": ""
    },
    {
      "sno": 2,
      "desc": "Short point (up to 3 mtr.)",
      "qty": "52",
      "rate": "256",
      "amt": "13312"
    },
    {
      "sno": 3,
      "desc": "Medium point (up to 6 mtr.)",
      "qty": "48",
      "rate": "472",
      "amt": "22656"
    },
    {
      "sno": 4,
      "desc": "Long point  (up to 10 mtr.)",
      "qty": "52",
      "rate": "662",
      "amt": "34424"
    },
    {
      "sno": 5,
      "desc": "Rewiring of 3/5 pin 6 amp. Light plug po",
      "qty": "",
      "rate": "",
      "amt": ""
    },
    {
      "sno": 6,
      "desc": "On board",
      "qty": "102",
      "rate": "136",
      "amt": "13872"
    },
    {
      "sno": 7,
      "desc": "P & F ISI marked (IS:3854) 6 amp. flush ",
      "qty": "8",
      "rate": "23",
      "amt": "184"
    },
    {
      "sno": 8,
      "desc": "Total",
      "qty": "",
      "rate": "",
      "amt": "84448"
    },
    {
      "sno": 9,
      "desc": "Add Tender Premium",
      "qty": "5.11",
      "rate": "Above",
      "amt": "4315"
    },
    {
      "sno": 10,
      "desc": "Grand Total",
      "qty": "",
      "rate": "",
      "amt": "88763"
    }
  ],
  "grand_total": 261974.0
}